gw_wispy-0.5.0.data/scripts/wispy_autoencoder_fit
gw_wispy-0.5.0.data/scripts/wispy_generate_training_data
gw_wispy-0.5.0.data/scripts/wispy_make_explorer_workflow
gw_wispy-0.5.0.data/scripts/wispy_plot_metrics
wispy/__init__.py
wispy/callbacks.py
wispy/lalutils.py
wispy/logger.py
wispy/model_utils.py
wispy/mscalev2.py
wispy/mscalev3.py
wispy/mscalev4.py
wispy/mscalev5.py
wispy/resnet.py
wispy/rotations.py
wispy/templates.py
wispy/utils.py
wispy/waveutils.py
gw_wispy-0.5.0.dist-info/LICENSE
gw_wispy-0.5.0.dist-info/METADATA
gw_wispy-0.5.0.dist-info/WHEEL
gw_wispy-0.5.0.dist-info/top_level.txt
gw_wispy-0.5.0.dist-info/RECORD
