Metadata-Version: 2.1
Name: gw-wispy
Version: 0.5.0
Summary: Neural Network Based Waveform Modelling
Home-page: https://gitlab.com/SpaceTimeKhantinuum/wispy
Author: Sebastian Khan
Author-email: KhanS22@Cardiff.ac.uk
License: UNKNOWN
Platform: UNKNOWN
Classifier: Programming Language :: Python :: 3
Requires-Python: >=3.6
